mirrorhour/__init__.py
mirrorhour/cli.py
mirrorhour/core.py
mirrorhour-0.1.0.dist-info/METADATA
mirrorhour-0.1.0.dist-info/WHEEL
mirrorhour-0.1.0.dist-info/entry_points.txt
mirrorhour-0.1.0.dist-info/licenses/LICENSE
mirrorhour-0.1.0.dist-info/RECORD
