Metadata-Version: 2.4
Name: mirrorhour
Version: 0.1.0
Summary: Utilities to detect and work with mirror hours (HH:HH) in local time or arbitrary timezones.
Project-URL: Homepage, https://github.com/XaviDev41/mirrorhour
Project-URL: Issues, https://github.com/XaviDev41/mirrorhour/issues
Author-email: XaviDev41 <4152@xavi.com.es>
License: MIT
License-File: LICENSE
Keywords: datetime,hora espejo,mirror hour,time
Classifier: License :: OSI Approved :: MIT License
Classifier: Operating System :: OS Independent
Classifier: Programming Language :: Python :: 3
Requires-Python: >=3.9
Provides-Extra: cli
Requires-Dist: tzdata>=2024.1; extra == 'cli'
